surquest/utils/randomizer/__init__.py
surquest/utils/randomizer/randomizer.py
surquest_utils_random_string_generator-0.0.1.dist-info/METADATA
surquest_utils_random_string_generator-0.0.1.dist-info/WHEEL
surquest_utils_random_string_generator-0.0.1.dist-info/licenses/LICENSE
surquest_utils_random_string_generator-0.0.1.dist-info/RECORD
