Metadata-Version: 2.1
Name: surquest-utils-random-string-generator
Version: 0.0.1
Summary: Randimizer generates timstamped unique random strings with minimal collision probability.
Project-URL: Homepage, https://github.com/surquest/python-random-generator
Project-URL: Bug Tracker, https://github.com/surquest/python-random-generator/issues
Author-email: Michal Švarc <michal.svarc@surquest.com>
License-File: LICENSE
Provides-Extra: test
Requires-Dist: pytest-cov==4.0.0; extra == 'test'
Requires-Dist: pytest==7.2.1; extra == 'test'
